{
    "drinks": [
      {
        "idDrink": "15092",
        "strDrink": "Pysch Vitamin Light",
        "strDrinkAlternate": null,
        "strDrinkES": null,
        "strDrinkDE": null,
        "strDrinkFR": null,
        "strDrinkZH-HANS": null,
        "strDrinkZH-HANT": null,
        "strTags": null,
        "strVideo": null,
        "strCategory": "Ordinary Drink",
        "strIBA": null,
        "strAlcoholic": "Non alcoholic",
        "strGlass": "Collins Glass",
        "strInstructions": "Shake with ice.",
        "strInstructionsES": null,
        "strInstructionsDE": null,
        "strInstructionsFR": null,
        "strInstructionsZH-HANS": null,
        "strInstructionsZH-HANT": null,
        "strDrinkThumb": "https://www.thecocktaildb.com/images/media/drink/xsqsxw1441553580.jpg",
        "strIngredient1": "Orange juice",
        "strIngredient2": "Apple juice",
        "strIngredient3": "Pineapple juice",
        "strIngredient4": "Ice",
        "strIngredient5": "",
        "strIngredient6": "",
        "strIngredient7": "",
        "strIngredient8": "",
        "strIngredient9": "",
        "strIngredient10": "",
        "strIngredient11": "",
        "strIngredient12": "",
        "strIngredient13": "",
        "strIngredient14": "",
        "strIngredient15": "",
        "strMeasure1": "1 part ",
        "strMeasure2": "1 part ",
        "strMeasure3": "1 part ",
        "strMeasure4": "\n",
        "strMeasure5": "\n",
        "strMeasure6": "\n",
        "strMeasure7": "\n",
        "strMeasure8": "\n",
        "strMeasure9": "\n",
        "strMeasure10": "",
        "strMeasure11": "",
        "strMeasure12": "",
        "strMeasure13": "",
        "strMeasure14": "",
        "strMeasure15": "",
        "strCreativeCommonsConfirmed": "No",
        "dateModified": "2015-09-06 16:33:00"
      },
      {
        "idDrink": "15092",
        "strDrink": "Pysch Vitamin Light",
        "strDrinkAlternate": null,
        "strDrinkES": null,
        "strDrinkDE": null,
        "strDrinkFR": null,
        "strDrinkZH-HANS": null,
        "strDrinkZH-HANT": null,
        "strTags": null,
        "strVideo": null,
        "strCategory": "Ordinary Drink",
        "strIBA": null,
        "strAlcoholic": "Non alcoholic",
        "strGlass": "Collins Glass",
        "strInstructions": "Shake with ice.",
        "strInstructionsES": null,
        "strInstructionsDE": null,
        "strInstructionsFR": null,
        "strInstructionsZH-HANS": null,
        "strInstructionsZH-HANT": null,
        "strDrinkThumb": "https://www.thecocktaildb.com/images/media/drink/xsqsxw1441553580.jpg",
        "strIngredient1": "Orange juice",
        "strIngredient2": "Apple juice",
        "strIngredient3": "Pineapple juice",
        "strIngredient4": "Ice",
        "strIngredient5": "fdgdfg",
        "strIngredient6": "fdgdfg",
        "strIngredient7": "fgdgdfgfdgfdgdf",
        "strIngredient8": "",
        "strIngredient9": "",
        "strIngredient10": "",
        "strIngredient11": "",
        "strIngredient12": "",
        "strIngredient13": "",
        "strIngredient14": "",
        "strIngredient15": "",
        "strMeasure1": "1 part ",
        "strMeasure2": "1 part ",
        "strMeasure3": "1 part ",
        "strMeasure4": "\n",
        "strMeasure5": "\n",
        "strMeasure6": "\n",
        "strMeasure7": "\n",
        "strMeasure8": "\n",
        "strMeasure9": "\n",
        "strMeasure10": "",
        "strMeasure11": "",
        "strMeasure12": "",
        "strMeasure13": "",
        "strMeasure14": "",
        "strMeasure15": "",
        "strCreativeCommonsConfirmed": "No",
        "dateModified": "2015-09-06 16:33:00"
      }
    ]
  }